{"ranking":[{"name":"Afghanistan","value":103324},{"name":"Albania","value":43457},{"name":"Algeria","value":108448},{"name":"Andorra","value":16094},{"name":"Angola","value":71496},{"name":"Argentina","value":199981},{"name":"Armenia","value":103778},{"name":"Australia","value":345955},{"name":"Austria","value":316739},{"name":"Azerbaijan","value":113173},{"name":"Bahrain","value":15722},{"name":"Bangladesh","value":228379},{"name":"Belarus","value":95215},{"name":"Belgium","value":329224},{"name":"Benin","value":70161},{"name":"Bhutan","value":10278},{"name":"Bolivia","value":66579},{"name":"Bosnia and Herz.","value":372},{"name":"Botswana","value":19475},{"name":"Brazil","value":247931},{"name":"Bulgaria","value":227118},{"name":"Burkina Faso","value":8174},{"name":"Burundi","value":18339},{"name":"Cambodia","value":59949},{"name":"Cameroon","value":144909},{"name":"Canada","value":413388},{"name":"Chad","value":2788},{"name":"Chile","value":142917},{"name":"China","value":371008},{"name":"Colombia","value":156934},{"name":"Congo","value":31777},{"name":"Croatia","value":143277},{"name":"Cuba","value":62204},{"name":"Cyprus","value":90526},{"name":"Czechia","value":316761},{"name":"Denmark","value":278030},{"name":"Dominican Rep.","value":37390},{"name":"Ecuador","value":127953},{"name":"Egypt","value":242503},{"name":"El Salvador","value":48148},{"name":"Estonia","value":125554},{"name":"Ethiopia","value":373119},{"name":"Finland","value":291682},{"name":"France","value":536932},{"name":"Georgia","value":150781},{"name":"Germany","value":606645},{"name":"Ghana","value":310103},{"name":"Greece","value":168173},{"name":"Guatemala","value":83302},{"name":"Honduras","value":43895},{"name":"Hong Kong","value":193349},{"name":"Hungary","value":194907},{"name":"Iceland","value":55381},{"name":"India","value":315537},{"name":"Indonesia","value":316776},{"name":"Iran","value":225401},{"name":"Iraq","value":77047},{"name":"Ireland","value":167104},{"name":"Israel","value":241125},{"name":"Italy","value":373130},{"name":"Jamaica","value":54600},{"name":"Japan","value":530278},{"name":"Jordan","value":81569},{"name":"Kazakhstan","value":80781},{"name":"Kenya","value":480543},{"name":"Kuwait","value":16188},{"name":"Laos","value":6280},{"name":"Latvia","value":75685},{"name":"Lithuania","value":89409},{"name":"Luxembourg","value":62092},{"name":"Madagascar","value":81451},{"name":"Malawi","value":48852},{"name":"Malaysia","value":145980},{"name":"Maldives","value":7657},{"name":"Mali","value":13185},{"name":"Malta","value":40760},{"name":"Mauritania","value":4130},{"name":"Mauritius","value":30597},{"name":"Mexico","value":158393},{"name":"Moldova","value":54724},{"name":"Mongolia","value":40670},{"name":"Montenegro","value":52050},{"name":"Morocco","value":236610},{"name":"Mozambique","value":51238},{"name":"Myanmar","value":83465},{"name":"Namibia","value":18996},{"name":"Nepal","value":165978},{"name":"Netherlands","value":437673},{"name":"New Zealand","value":150580},{"name":"Nicaragua","value":99838},{"name":"Nigeria","value":321109},{"name":"Norway","value":302600},{"name":"Oman","value":21782},{"name":"Pakistan","value":218268},{"name":"Palestine","value":103803},{"name":"Panama","value":30914},{"name":"Paraguay","value":52178},{"name":"Peru","value":111020},{"name":"Philippines","value":238934},{"name":"Poland","value":358896},{"name":"Portugal","value":252451},{"name":"Qatar","value":22437},{"name":"Romania","value":191248},{"name":"Russia","value":228460},{"name":"Rwanda","value":258068},{"name":"San Marino","value":2079},{"name":"Saudi Arabia","value":40560},{"name":"Senegal","value":48842},{"name":"Serbia","value":160766},{"name":"Sierra Leone","value":6433},{"name":"Singapore","value":241934},{"name":"Slovakia","value":134603},{"name":"Slovenia","value":106381},{"name":"South Africa","value":147663},{"name":"South Korea","value":319946},{"name":"Spain","value":399113},{"name":"Sri Lanka","value":162065},{"name":"Sudan","value":42946},{"name":"Sweden","value":316410},{"name":"Switzerland","value":358963},{"name":"Syria","value":35242},{"name":"Taiwan","value":313106},{"name":"Tanzania","value":120327},{"name":"Thailand","value":214564},{"name":"Tunisia","value":118801},{"name":"Turkey","value":190387},{"name":"Uganda","value":220302},{"name":"Ukraine","value":242044},{"name":"United Arab Emirates","value":814},{"name":"United Kingdom","value":416508},{"name":"United States of America","value":413958},{"name":"Uruguay","value":137380},{"name":"Uzbekistan","value":170578},{"name":"Venezuela","value":114636},{"name":"Vietnam","value":195541},{"name":"Yemen","value":42111},{"name":"Zambia","value":50843},{"name":"Zambia","value":56094}]}
