{"ranking":[{"name":"Afghanistan","value":95791},{"name":"Albania","value":40868},{"name":"Algeria","value":109936},{"name":"Andorra","value":15082},{"name":"Angola","value":69676},{"name":"Argentina","value":189659},{"name":"Armenia","value":100341},{"name":"Australia","value":349657},{"name":"Austria","value":312458},{"name":"Azerbaijan","value":100743},{"name":"Bahrain","value":15383},{"name":"Bangladesh","value":234251},{"name":"Belarus","value":98326},{"name":"Belgium","value":322547},{"name":"Benin","value":69325},{"name":"Bhutan","value":8321},{"name":"Bolivia","value":65855},{"name":"Bosnia and Herz.","value":372},{"name":"Botswana","value":17034},{"name":"Brazil","value":232613},{"name":"Bulgaria","value":224493},{"name":"Burkina Faso","value":8436},{"name":"Burundi","value":18920},{"name":"Cambodia","value":62525},{"name":"Cameroon","value":137862},{"name":"Canada","value":394689},{"name":"Chad","value":2019},{"name":"Chile","value":148161},{"name":"China","value":374064},{"name":"Colombia","value":154678},{"name":"Congo","value":31242},{"name":"Croatia","value":141353},{"name":"Cuba","value":61543},{"name":"Cyprus","value":88706},{"name":"Czechia","value":311843},{"name":"Denmark","value":277277},{"name":"Dominican Rep.","value":35970},{"name":"Ecuador","value":128372},{"name":"Egypt","value":239218},{"name":"El Salvador","value":43782},{"name":"Estonia","value":139352},{"name":"Ethiopia","value":372022},{"name":"Finland","value":290404},{"name":"France","value":533898},{"name":"Georgia","value":145132},{"name":"Germany","value":604859},{"name":"Ghana","value":305240},{"name":"Greece","value":167078},{"name":"Guatemala","value":79594},{"name":"Honduras","value":44979},{"name":"Hong Kong","value":196329},{"name":"Hungary","value":188206},{"name":"Iceland","value":53209},{"name":"India","value":320231},{"name":"Indonesia","value":320940},{"name":"Iran","value":216850},{"name":"Iraq","value":86460},{"name":"Ireland","value":163384},{"name":"Israel","value":247105},{"name":"Italy","value":371514},{"name":"Jamaica","value":56129},{"name":"Japan","value":521473},{"name":"Jordan","value":93786},{"name":"Kazakhstan","value":79069},{"name":"Kenya","value":470969},{"name":"Kuwait","value":15449},{"name":"Laos","value":6764},{"name":"Latvia","value":74243},{"name":"Lithuania","value":89146},{"name":"Luxembourg","value":65853},{"name":"Madagascar","value":75391},{"name":"Malawi","value":47275},{"name":"Malaysia","value":143752},{"name":"Maldives","value":7683},{"name":"Mali","value":13914},{"name":"Malta","value":41250},{"name":"Mauritania","value":3708},{"name":"Mauritius","value":28128},{"name":"Mexico","value":154751},{"name":"Moldova","value":54770},{"name":"Mongolia","value":32645},{"name":"Montenegro","value":51699},{"name":"Morocco","value":209182},{"name":"Mozambique","value":48290},{"name":"Myanmar","value":78989},{"name":"Namibia","value":17796},{"name":"Nepal","value":173071},{"name":"Netherlands","value":428390},{"name":"New Zealand","value":150759},{"name":"Nicaragua","value":96820},{"name":"Nigeria","value":343737},{"name":"Norway","value":293969},{"name":"Oman","value":21631},{"name":"Pakistan","value":218909},{"name":"Palestine","value":99370},{"name":"Panama","value":27657},{"name":"Paraguay","value":50954},{"name":"Peru","value":106623},{"name":"Philippines","value":218458},{"name":"Poland","value":354249},{"name":"Portugal","value":251794},{"name":"Qatar","value":20479},{"name":"Romania","value":176828},{"name":"Russia","value":233979},{"name":"Rwanda","value":251772},{"name":"San Marino","value":2640},{"name":"Saudi Arabia","value":41844},{"name":"Senegal","value":48407},{"name":"Serbia","value":159090},{"name":"Sierra Leone","value":6415},{"name":"Singapore","value":240098},{"name":"Slovakia","value":140736},{"name":"Slovenia","value":104935},{"name":"South Africa","value":140987},{"name":"South Korea","value":321319},{"name":"Spain","value":392241},{"name":"Sri Lanka","value":169342},{"name":"Sudan","value":38900},{"name":"Sweden","value":315970},{"name":"Switzerland","value":347037},{"name":"Syria","value":35718},{"name":"Taiwan","value":307494},{"name":"Tanzania","value":115986},{"name":"Thailand","value":223237},{"name":"Tunisia","value":121596},{"name":"Turkey","value":194940},{"name":"Uganda","value":218473},{"name":"Ukraine","value":232144},{"name":"United Arab Emirates","value":337},{"name":"United Kingdom","value":406949},{"name":"United States of America","value":400345},{"name":"Uruguay","value":134312},{"name":"Uzbekistan","value":187288},{"name":"Venezuela","value":109088},{"name":"Vietnam","value":204946},{"name":"Yemen","value":40155},{"name":"Zambia","value":53869},{"name":"Zambia","value":60514}]}
