{"ranking":[{"name":"Afghanistan","value":105356},{"name":"Albania","value":37388},{"name":"Algeria","value":107702},{"name":"Andorra","value":17425},{"name":"Angola","value":71864},{"name":"Argentina","value":191210},{"name":"Armenia","value":100904},{"name":"Australia","value":350062},{"name":"Austria","value":316582},{"name":"Azerbaijan","value":111674},{"name":"Bahrain","value":15141},{"name":"Bangladesh","value":240502},{"name":"Belarus","value":96682},{"name":"Belgium","value":324096},{"name":"Benin","value":65392},{"name":"Bhutan","value":11183},{"name":"Bolivia","value":66001},{"name":"Bosnia and Herz.","value":372},{"name":"Botswana","value":19226},{"name":"Brazil","value":244338},{"name":"Bulgaria","value":224392},{"name":"Burkina Faso","value":6567},{"name":"Burundi","value":18492},{"name":"Cambodia","value":58757},{"name":"Cameroon","value":144408},{"name":"Canada","value":403745},{"name":"Chad","value":2949},{"name":"Chile","value":143974},{"name":"China","value":347275},{"name":"Colombia","value":157235},{"name":"Congo","value":35523},{"name":"Croatia","value":138230},{"name":"Cuba","value":62956},{"name":"Cyprus","value":88198},{"name":"Czechia","value":316051},{"name":"Denmark","value":274703},{"name":"Dominican Rep.","value":37425},{"name":"Ecuador","value":129238},{"name":"Egypt","value":252097},{"name":"El Salvador","value":49303},{"name":"Estonia","value":118460},{"name":"Ethiopia","value":360270},{"name":"Finland","value":288338},{"name":"France","value":526294},{"name":"Georgia","value":150349},{"name":"Germany","value":611858},{"name":"Ghana","value":304384},{"name":"Greece","value":170864},{"name":"Guatemala","value":84427},{"name":"Honduras","value":44780},{"name":"Hong Kong","value":189080},{"name":"Hungary","value":201719},{"name":"Iceland","value":58840},{"name":"India","value":310199},{"name":"Indonesia","value":326797},{"name":"Iran","value":222169},{"name":"Iraq","value":70068},{"name":"Ireland","value":166715},{"name":"Israel","value":245538},{"name":"Italy","value":372594},{"name":"Jamaica","value":53985},{"name":"Japan","value":517984},{"name":"Jordan","value":74382},{"name":"Kazakhstan","value":80411},{"name":"Kenya","value":443781},{"name":"Kuwait","value":16064},{"name":"Laos","value":5953},{"name":"Latvia","value":70849},{"name":"Lithuania","value":88941},{"name":"Luxembourg","value":62342},{"name":"Madagascar","value":76209},{"name":"Malawi","value":44596},{"name":"Malaysia","value":144572},{"name":"Maldives","value":8760},{"name":"Mali","value":12129},{"name":"Malta","value":41349},{"name":"Mauritania","value":4307},{"name":"Mauritius","value":30147},{"name":"Mexico","value":155361},{"name":"Moldova","value":54377},{"name":"Mongolia","value":40790},{"name":"Montenegro","value":55815},{"name":"Morocco","value":235806},{"name":"Mozambique","value":51028},{"name":"Myanmar","value":94682},{"name":"Namibia","value":18537},{"name":"Nepal","value":172856},{"name":"Netherlands","value":442225},{"name":"New Zealand","value":149622},{"name":"Nicaragua","value":100778},{"name":"Nigeria","value":306202},{"name":"Norway","value":301389},{"name":"Oman","value":20992},{"name":"Pakistan","value":214599},{"name":"Palestine","value":102890},{"name":"Panama","value":30669},{"name":"Paraguay","value":53854},{"name":"Peru","value":109302},{"name":"Philippines","value":248548},{"name":"Poland","value":358143},{"name":"Portugal","value":258861},{"name":"Qatar","value":20810},{"name":"Romania","value":193793},{"name":"Russia","value":233211},{"name":"Rwanda","value":252673},{"name":"San Marino","value":2105},{"name":"Saudi Arabia","value":37697},{"name":"Senegal","value":46553},{"name":"Serbia","value":160208},{"name":"Sierra Leone","value":7632},{"name":"Singapore","value":233428},{"name":"Slovakia","value":132142},{"name":"Slovenia","value":107040},{"name":"South Africa","value":144642},{"name":"South Korea","value":308906},{"name":"Spain","value":398329},{"name":"Sri Lanka","value":160381},{"name":"Sudan","value":46768},{"name":"Sweden","value":309476},{"name":"Switzerland","value":358472},{"name":"Syria","value":33827},{"name":"Taiwan","value":308926},{"name":"Tanzania","value":119702},{"name":"Thailand","value":221826},{"name":"Tunisia","value":116813},{"name":"Turkey","value":185089},{"name":"Uganda","value":209135},{"name":"Ukraine","value":239519},{"name":"United Arab Emirates","value":771},{"name":"United Kingdom","value":416581},{"name":"United States of America","value":415027},{"name":"Uruguay","value":124353},{"name":"Uzbekistan","value":176967},{"name":"Venezuela","value":115822},{"name":"Vietnam","value":201131},{"name":"Yemen","value":31321},{"name":"Zambia","value":50754},{"name":"Zambia","value":54712}]}
